{
  "id": "6db38a9d-6651-468b-9acf-0750576b9b15",
  "prevId": "7cb3c52e-799f-4a70-b24b-58454fd431ce",
  "version": "7",
  "dialect": "postgresql",
  "tables": {
    "public.production_orders": {
      "name": "production_orders",
      "schema": "",
      "columns": {
        "id": {
          "name": "id",
          "type": "uuid",
          "primaryKey": true,
          "notNull": true,
          "default": "gen_random_uuid()"
        },
        "order_number": {
          "name": "order_number",
          "type": "text",
          "primaryKey": false,
          "notNull": true
        },
        "customer": {
          "name": "customer",
          "type": "text",
          "primaryKey": false,
          "notNull": true
        },
        "product": {
          "name": "product",
          "type": "text",
          "primaryKey": false,
          "notNull": true
        },
        "weight_lbs": {
          "name": "weight_lbs",
          "type": "numeric(10, 2)",
          "primaryKey": false,
          "notNull": true
        },
        "delivery_time": {
          "name": "delivery_time",
          "type": "text",
          "primaryKey": false,
          "notNull": true
        },
        "state": {
          "name": "state",
          "type": "production_state",
          "typeSchema": "public",
          "primaryKey": false,
          "notNull": true
        },
        "mill_line": {
          "name": "mill_line",
          "type": "mill_line",
          "typeSchema": "public",
          "primaryKey": false,
          "notNull": true
        },
        "texture_type": {
          "name": "texture_type",
          "type": "text",
          "primaryKey": false,
          "notNull": false
        },
        "line_code": {
          "name": "line_code",
          "type": "text",
          "primaryKey": false,
          "notNull": false
        },
        "early_delivery_date": {
          "name": "early_delivery_date",
          "type": "date",
          "primaryKey": false,
          "notNull": false
        },
        "version": {
          "name": "version",
          "type": "integer",
          "primaryKey": false,
          "notNull": true,
          "default": 1
        },
        "created_by": {
          "name": "created_by",
          "type": "text",
          "primaryKey": false,
          "notNull": true
        },
        "created_at": {
          "name": "created_at",
          "type": "timestamp with time zone",
          "primaryKey": false,
          "notNull": true,
          "default": "now()"
        },
        "updated_at": {
          "name": "updated_at",
          "type": "timestamp with time zone",
          "primaryKey": false,
          "notNull": true,
          "default": "now()"
        }
      },
      "indexes": {
        "idx_orders_state": {
          "name": "idx_orders_state",
          "columns": [
            {
              "expression": "state",
              "isExpression": false,
              "asc": true,
              "nulls": "last"
            }
          ],
          "isUnique": false,
          "concurrently": false,
          "method": "btree",
          "with": {}
        },
        "idx_orders_mill_line": {
          "name": "idx_orders_mill_line",
          "columns": [
            {
              "expression": "mill_line",
              "isExpression": false,
              "asc": true,
              "nulls": "last"
            }
          ],
          "isUnique": false,
          "concurrently": false,
          "method": "btree",
          "with": {}
        },
        "idx_orders_order_number": {
          "name": "idx_orders_order_number",
          "columns": [
            {
              "expression": "order_number",
              "isExpression": false,
              "asc": true,
              "nulls": "last"
            }
          ],
          "isUnique": true,
          "concurrently": false,
          "method": "btree",
          "with": {}
        }
      },
      "foreignKeys": {},
      "compositePrimaryKeys": {},
      "uniqueConstraints": {},
      "policies": {},
      "checkConstraints": {},
      "isRLSEnabled": false
    },
    "public.order_events": {
      "name": "order_events",
      "schema": "",
      "columns": {
        "id": {
          "name": "id",
          "type": "uuid",
          "primaryKey": true,
          "notNull": true,
          "default": "gen_random_uuid()"
        },
        "order_id": {
          "name": "order_id",
          "type": "uuid",
          "primaryKey": false,
          "notNull": true
        },
        "from_state": {
          "name": "from_state",
          "type": "production_state",
          "typeSchema": "public",
          "primaryKey": false,
          "notNull": false
        },
        "to_state": {
          "name": "to_state",
          "type": "production_state",
          "typeSchema": "public",
          "primaryKey": false,
          "notNull": true
        },
        "changed_by": {
          "name": "changed_by",
          "type": "text",
          "primaryKey": false,
          "notNull": true
        },
        "changed_at": {
          "name": "changed_at",
          "type": "timestamp with time zone",
          "primaryKey": false,
          "notNull": true,
          "default": "now()"
        },
        "note": {
          "name": "note",
          "type": "text",
          "primaryKey": false,
          "notNull": false
        }
      },
      "indexes": {
        "idx_events_order_id_changed_at_desc": {
          "name": "idx_events_order_id_changed_at_desc",
          "columns": [
            {
              "expression": "order_id",
              "isExpression": false,
              "asc": true,
              "nulls": "last"
            },
            {
              "expression": "changed_at",
              "isExpression": false,
              "asc": false,
              "nulls": "last"
            }
          ],
          "isUnique": false,
          "concurrently": false,
          "method": "btree",
          "with": {}
        }
      },
      "foreignKeys": {
        "order_events_order_id_production_orders_id_fk": {
          "name": "order_events_order_id_production_orders_id_fk",
          "tableFrom": "order_events",
          "tableTo": "production_orders",
          "columnsFrom": [
            "order_id"
          ],
          "columnsTo": [
            "id"
          ],
          "onDelete": "cascade",
          "onUpdate": "no action"
        }
      },
      "compositePrimaryKeys": {},
      "uniqueConstraints": {},
      "policies": {},
      "checkConstraints": {},
      "isRLSEnabled": false
    },
    "public.import_batches": {
      "name": "import_batches",
      "schema": "",
      "columns": {
        "id": {
          "name": "id",
          "type": "uuid",
          "primaryKey": true,
          "notNull": true,
          "default": "gen_random_uuid()"
        },
        "file_name": {
          "name": "file_name",
          "type": "text",
          "primaryKey": false,
          "notNull": true
        },
        "row_count": {
          "name": "row_count",
          "type": "integer",
          "primaryKey": false,
          "notNull": true
        },
        "imported_by": {
          "name": "imported_by",
          "type": "text",
          "primaryKey": false,
          "notNull": true
        },
        "imported_at": {
          "name": "imported_at",
          "type": "timestamp with time zone",
          "primaryKey": false,
          "notNull": true,
          "default": "now()"
        }
      },
      "indexes": {},
      "foreignKeys": {},
      "compositePrimaryKeys": {},
      "uniqueConstraints": {},
      "policies": {},
      "checkConstraints": {},
      "isRLSEnabled": false
    },
    "public.users": {
      "name": "users",
      "schema": "",
      "columns": {
        "id": {
          "name": "id",
          "type": "text",
          "primaryKey": true,
          "notNull": true
        },
        "display_name": {
          "name": "display_name",
          "type": "text",
          "primaryKey": false,
          "notNull": false
        },
        "email": {
          "name": "email",
          "type": "text",
          "primaryKey": false,
          "notNull": false
        },
        "last_seen_at": {
          "name": "last_seen_at",
          "type": "timestamp with time zone",
          "primaryKey": false,
          "notNull": false,
          "default": "now()"
        },
        "created_at": {
          "name": "created_at",
          "type": "timestamp with time zone",
          "primaryKey": false,
          "notNull": true,
          "default": "now()"
        }
      },
      "indexes": {},
      "foreignKeys": {},
      "compositePrimaryKeys": {},
      "uniqueConstraints": {},
      "policies": {},
      "checkConstraints": {},
      "isRLSEnabled": false
    }
  },
  "enums": {
    "public.mill_line": {
      "name": "mill_line",
      "schema": "public",
      "values": [
        "Premix",
        "Excel",
        "CGM"
      ]
    },
    "public.production_state": {
      "name": "production_state",
      "schema": "public",
      "values": [
        "Pending",
        "Mixing",
        "Completed",
        "Blocked"
      ]
    }
  },
  "schemas": {},
  "sequences": {},
  "roles": {},
  "policies": {},
  "views": {},
  "_meta": {
    "columns": {},
    "schemas": {},
    "tables": {}
  }
}